LICENSE
MANIFEST.in
NEWS.rst
README.rst
setup.py
sampledata/__init__.py
sampledata/exceptions.py
sampledata/helper.py
sampledata/image_generators.py
sampledata/loremipsum.py
sampledata.egg-info/PKG-INFO
sampledata.egg-info/SOURCES.txt
sampledata.egg-info/dependency_links.txt
sampledata.egg-info/requires.txt
sampledata.egg-info/top_level.txt
sampledata/l10n/__init__.py
sampledata/l10n/cities.py
sampledata/l10n/names.py
sampledata/l10n/occupations.py
sampledata/l10n/skills.py
sampledata/l10n/cities/es.json
sampledata/l10n/cities/us.json
sampledata/l10n/names/cat.json
sampledata/l10n/names/es.json
sampledata/l10n/names/fr.json
sampledata/l10n/names/us.json
sampledata/l10n/occupations/us.json
sampledata/l10n/skills/es.json
sampledata/l10n/skills/us.json
sampledata/mixins/__init__.py
sampledata/mixins/image_mixin.py
sampledata/mixins/localized_mixin.py
sampledata/mixins/number_mixin.py
sampledata/mixins/other_mixin.py
sampledata/mixins/text_mixin.py
sampledata/mixins/time_mixin.py
sampledata/static/font.ttf
tests/__init__.py
tests/tests.py