Metadata-Version: 1.1
Name: sampledata
Version: 0.3.6
Summary: Helper class for generate sample data
Home-page: https://github.com/jespino/sampledata
Author: Jesús Espino García
Author-email: jespinog@gmail.com
License: BSD
Keywords: sample,data,example,loremipsum
Platform: UNKNOWN
Classifier: Programming Language :: Python
Classifier: Development Status :: 4 - Beta
Classifier: Intended Audience :: Developers
Classifier: License :: OSI Approved :: BSD License
Classifier: Operating System :: OS Independent
Classifier: Programming Language :: Python
Classifier: Topic :: Internet :: WWW/HTTP
